{"name":"Plump free icons","total":1499,"author":{"name":"Streamline","url":"https://github.com/webalys-hq/streamline-vectors"},"license":{"title":"CC BY 4.0","spdx":"CC-BY-4.0","url":"https://creativecommons.org/licenses/by/4.0/"},"samples":["smiley-indiferent","music-note-2","web","circle-clock","loading-horizontal-2","steps-1-solid"],"height":24,"category":"UI 24px","palette":false,"id":"streamline-plump","icons":["3d-coordinate-axis","3d-coordinate-axis-remix","3d-coordinate-axis-solid","add-bell-notification","add-bell-notification-remix","add-bell-notification-solid","add-layer-2","add-layer-2-remix","add-layer-2-solid","ai-edit-robot","ai-edit-robot-remix","ai-edit-robot-solid","ai-generate-portrait-image-spark","ai-generate-portrait-image-spark-remix","ai-generate-portrait-image-spark-solid","ai-generate-variation-spark","ai-generate-variation-spark-remix","ai-generate-variation-spark-solid","ai-generate-voice-robot-2","ai-generate-voice-robot-2-remix","ai-generate-voice-robot-2-solid","ai-science-robot","ai-science-robot-remix","ai-science-robot-solid","ai-technology-spark","ai-technology-spark-remix","ai-technology-spark-solid","airplane-disabled","airplane-disabled-remix","airplane-disabled-solid","airplane-enabled","airplane-enabled-remix","airplane-enabled-solid","airport-security","airport-security-remix","airport-security-solid","alien","alien-remix","alien-solid","align-object-left","align-object-left-remix","align-object-left-solid","align-right","align-right-1-remix","align-right-solid","align-selection","align-selection-remix","align-selection-solid","allergens-fish-remix","allergens-gluten-remix","ampersand","ampersand-remix","ampersand-solid","announcement-megaphone","announcement-megaphone-remix","announcement-megaphone-solid","application-add","application-add-remix","application-add-solid","archive-box","archive-box-remix","archive-box-solid","arrow-cursor-1","arrow-cursor-1-remix","arrow-cursor-1-solid","arrow-cursor-move","arrow-cursor-move-remix","arrow-cursor-move-solid","arrow-curvy-both-direction-2","arrow-curvy-both-direction-2-solid","arrow-diagonal-2","arrow-diagonal-2-solid","arrow-expand","arrow-expand-solid","arrow-right-circle-1","arrow-right-circle-1-solid","arrow-right-circle-2","arrow-right-circle-2-solid","arrow-roadmap","arrow-roadmap-solid","arrow-transfer-horizontal-square","arrow-transfer-horizontal-square-solid","arrow-turn-down-large","arrow-turn-down-large-solid","arrow-up-4","arrow-up-4-solid","ascending-alphabetical-order","ascending-alphabetical-order-remix","ascending-alphabetical-order-solid","atom","atom-remix","atom-solid","attribution","attribution-remix","attribution-solid","auto-flash","auto-flash-remix","auto-flash-solid","bag","bag-remix","bag-solid","bag-suitcase-4","bag-suitcase-4-remix","bag-suitcase-4-solid","ball","ball-remix","ball-solid","balloon","balloon-remix","balloon-solid","battery-charging","battery-charging-remix","battery-charging-solid","battery-low-1-remix","battery-low-3","battery-low-3-solid","beach","beach-remix","beach-solid","beer-pitch","beer-pitch-remix","beer-pitch-solid","bell","bell-remix","bell-solid","bicycle-bike","bicycle-bike-remix","bicycle-bike-solid","bill-1-remix","binoculars","binoculars-remix","binoculars-solid","bitcoin-circle-1","bitcoin-circle-1-remix","bitcoin-circle-1-solid","block-1","block-1-remix","block-1-solid","bluetooth","bluetooth-remix","bluetooth-solid","bomb","bomb-remix","bomb-solid","book-1","book-1-remix","book-1-solid","bookmark","bookmark-1-remix","bookmark-solid","border-frame","border-frame-remix","border-frame-solid","bowl-chop-stick","bowl-chop-stick-remix","bowl-chop-stick-solid","box-waterproof","box-waterproof-remix","box-waterproof-solid","braille-blind","braille-blind-remix","braille-blind-solid","broken-link-2","broken-link-2-remix","broken-link-2-solid","browser-code-1","browser-code-1-remix","browser-code-1-solid","browser-website-1","browser-website-1-remix","browser-website-1-solid","bug","bug-remix","bug-solid","bug-virus-browser","bug-virus-browser-remix","bug-virus-browser-solid","building-office","building-office-remix","building-office-solid","burger","burger-remix","burger-solid","bus","bus-remix","bus-solid","business-progress-bar-2","business-progress-bar-2-remix","business-progress-bar-2-solid","button-play-circle","button-play-circle-remix","button-play-circle-solid","button-power-1","button-power-1-remix","button-power-1-solid","cable-split","cable-split-remix","cable-split-solid","cake-slice","cake-slice-remix","cake-slice-solid","calculator-1","calculator-1-remix","calculator-1-solid","calendar-add","calendar-add-remix","calendar-add-solid","calendar-check","calendar-check-remix","calendar-check-solid","calendar-heart","calendar-heart-remix","calendar-heart-solid","calendar-mark","calendar-mark-remix","calendar-mark-solid","calendar-note-remix","call-center-support-service","call-center-support-service-remix","call-center-support-service-solid","call-hang-up","call-hang-up-remix","call-hang-up-solid","camera-1","camera-1-remix","camera-1-solid","camera-video","camera-video-remix","camera-video-solid","candle","candle-remix","candle-solid","cao-dai","cao-dai-remix","cao-dai-solid","card-game-diamond","card-game-diamond-remix","card-game-diamond-solid","change-background-transparent","change-background-transparent-remix","change-background-transparent-solid","charging","charging-remix","charging-solid","chat-bubble-oval-notification","chat-bubble-oval-notification-remix","chat-bubble-oval-notification-solid","chat-bubble-oval-smiley-1","chat-bubble-oval-smiley-1-remix","chat-bubble-oval-smiley-1-solid","chat-bubble-square-lock-remix","chat-bubble-square-question-remix","chat-bubble-square-warning","chat-bubble-square-warning-remix","chat-bubble-square-warning-solid","chat-bubble-text-square","chat-bubble-text-square-remix","chat-bubble-text-square-solid","chat-two-bubbles-oval","chat-two-bubbles-oval-remix","chat-two-bubbles-oval-solid","check-thick","check-thick-remix","check-thick-solid","cheese","cheese-remix","cheese-solid","chef-toque-hat","chef-toque-hat-remix","chef-toque-hat-solid","cherries","cherries-remix","cherries-solid","chess-pawn","chess-pawn-remix","chess-pawn-solid","circle-and-square-shape","circle-and-square-shape-remix","circle-and-square-shape-solid","circle-clock","circle-clock-remix","circle-clock-solid","class-lesson","class-lesson-remix","class-lesson-solid","clean-broom-wipe","clean-broom-wipe-remix","clean-broom-wipe-solid","cleaning-room-woman","cleaning-room-woman-remix","cleaning-room-woman-solid","cloud-data-transfer","cloud-data-transfer-remix","cloud-data-transfer-solid","cloud-off","cloud-off-remix","cloud-off-solid","code-monitor-2","code-monitor-2-remix","code-monitor-2-solid","coffee-bean","coffee-bean-remix","coffee-bean-solid","coffee-mug","coffee-mug-remix","coffee-mug-solid","cog","cog-1-remix","cog-automation","cog-automation-remix","cog-automation-solid","cog-solid","color-picker","color-picker-remix","color-picker-solid","command","command-remix","command-solid","compass-navigator","compass-navigator-remix","compass-navigator-solid","compress-pdf","compress-pdf-remix","compress-pdf-solid","computer-pc-desktop","computer-pc-desktop-remix","computer-pc-desktop-solid","contact-phonebook","contact-phonebook-remix","contact-phonebook-solid","content-statistic","content-statistic-remix","content-statistic-solid","controller-1","controller-1-remix","controller-1-solid","convert-pdf-1","convert-pdf-1-remix","convert-pdf-1-solid","creative-commons","creative-commons-remix","creative-commons-solid","credit-card-5","credit-card-5-remix","credit-card-5-solid","crop-selection","crop-selection-remix","crop-selection-solid","customer-support-3","customer-support-3-remix","customer-support-3-solid","customer-support-7","customer-support-7-remix","customer-support-7-solid","cut","cut-remix","cut-solid","cyborg-2","cyborg-2-remix","cyborg-2-solid","dark-dislay-mode","dark-dislay-mode-remix","dark-dislay-mode-solid","dashboard-1","dashboard-1-remix","dashboard-1-solid","dashboard-gauge-2","dashboard-gauge-2-solid","dashboard-gauge-medium-2-remix","database","database-remix","database-server-3","database-server-3-remix","database-server-3-solid","database-solid","deepfake-technology-1","deepfake-technology-1-remix","deepfake-technology-1-solid","delete-bookmark","delete-bookmark-remix","delete-bookmark-solid","delete-keyboard","delete-keyboard-remix","delete-keyboard-solid","delete-row","delete-row-remix","delete-row-solid","description","description-remix","description-solid","desktop-lock","desktop-lock-remix","desktop-lock-solid","device-database-encryption-1","device-database-encryption-1-remix","device-database-encryption-1-solid","diagonal-triangle-arrow-2-remix","dial-pad-finger-2","dial-pad-finger-2-remix","dial-pad-finger-2-solid","diamond-1","diamond-1-solid","diamond-2-remix","dices-entertainment-gaming-dices","dices-entertainment-gaming-dices-remix","dices-entertainment-gaming-dices-solid","disable-alarm","disable-alarm-remix","disable-alarm-solid","disable-heart","disable-heart-remix","disable-heart-solid","disable-protection","disable-protection-remix","disable-protection-solid","discount-percent-cutout","discount-percent-cutout-remix","discount-percent-cutout-solid","division-circle","division-circle-remix","division-circle-solid","dna","dna-remix","dna-solid","document-certificate","document-certificate-remix","document-certificate-solid","dog-1","dog-1-remix","dog-1-solid","dollar-coin","dollar-coin-remix","dollar-coin-solid","door","door-remix","door-solid","download-box-2","download-box-2-remix","download-box-2-solid","drop-down-menu","drop-down-menu-remix","drop-down-menu-solid","dropbox","dropbox-logo-remix","dropbox-solid","drum-stick","drum-stick-remix","drum-stick-solid","dumbell","dumbell-remix","dumbell-solid","ear-speciality","ear-speciality-remix","ear-speciality-solid","earpods","earpods-remix","earpods-solid","earth-1","earth-1-solid","earth-2-remix","electric-charging-station","electric-charging-station-remix","electric-charging-station-solid","electric-cord-1","electric-cord-1-remix","electric-cord-1-solid","email-attachment-document","email-attachment-document-remix","email-attachment-document-solid","empty-clipboard","empty-clipboard-remix","empty-clipboard-solid","end-point-branches","end-point-branches-remix","end-point-branches-solid","end-point-diamond","end-point-diamond-remix","end-point-diamond-solid","eraser","eraser-remix","eraser-solid","erlenmeyer-flask","erlenmeyer-flask-remix","erlenmeyer-flask-solid","escalator-up","escalator-up-remix","escalator-up-solid","exit-full-screen","exit-full-screen-remix","exit-full-screen-solid","expand-horizontal-2","expand-horizontal-2-solid","eye-optic","eye-optic-remix","eye-optic-solid","facebook-1","facebook-1-solid","facebook-logo-1-remix","factory-plant","factory-plant-remix","factory-plant-solid","fahrenheit","fahrenheit-remix","fahrenheit-solid","feather-pen","feather-pen-remix","feather-pen-solid","file-check-alternate","file-check-alternate-remix","file-check-alternate-solid","file-folder","file-folder-remix","file-folder-solid","file-report","file-report-remix","file-report-solid","file-search","file-search-remix","file-search-solid","fill-and-sign","fill-and-sign-remix","fill-and-sign-solid","film-slate","film-slate-remix","film-slate-solid","filter-1","filter-1-remix","filter-1-solid","fingerprint-2","fingerprint-2-remix","fingerprint-2-solid","fire-evacuation","fire-evacuation-remix","fire-evacuation-solid","firefighter-truck","firefighter-truck-remix","firefighter-truck-solid","fish","fish-solid","fit-height","fit-height-remix","fit-height-solid","fit-to-width-square","fit-to-width-square-solid","fit-width-remix","flash-1","flash-1-remix","flash-1-solid","flashlight","flashlight-remix","flashlight-solid","flip-horizontal-circle-1","flip-horizontal-circle-1-remix","flip-horizontal-circle-1-solid","floppy-disk","floppy-disk-remix","floppy-disk-solid","focus-points","focus-points-remix","focus-points-solid","food-truck-event-fair","food-truck-event-fair-remix","food-truck-event-fair-solid","fork-knife","fork-knife-remix","fork-knife-solid","fork-plate","fork-plate-remix","fork-plate-solid","fragile","fragile-remix","fragile-solid","fried-egg-breakfast","fried-egg-breakfast-remix","fried-egg-breakfast-solid","galaxy-2","galaxy-2-remix","galaxy-2-solid","gallery-2","gallery-2-remix","gallery-2-solid","gameboy","gameboy-remix","gameboy-solid","gift","gift-remix","gift-solid","give-gift","give-gift-remix","give-gift-solid","global-learning","global-learning-remix","global-learning-solid","global-warming-2","global-warming-2-remix","global-warming-2-solid","gold","gold-remix","gold-solid","government-building-1","government-building-1-remix","government-building-1-solid","graduation-cap","graduation-cap-remix","graduation-cap-solid","graph-arrow-user-increase","graph-arrow-user-increase-remix","graph-arrow-user-increase-solid","graph-bar-increase","graph-bar-increase-remix","graph-bar-increase-solid","graph-dot","graph-dot-remix","graph-dot-solid","graphic-template-website-ui","graphic-template-website-ui-remix","graphic-template-website-ui-solid","half-star-2","half-star-2-remix","half-star-2-solid","hand-held","hand-held-remix","hand-held-solid","hard-drive-2","hard-drive-2-remix","hard-drive-2-solid","heart-rate-pulse-graph","heart-rate-pulse-graph-remix","heart-rate-pulse-graph-solid","heater","heater-remix","heater-solid","help-chat-1","help-chat-1-solid","hierarchy-1","hierarchy-1-remix","hierarchy-1-solid","hierarchy-15","hierarchy-15-remix","hierarchy-15-solid","high-speed-train-side","high-speed-train-side-remix","high-speed-train-side-solid","home-1","home-1-remix","home-1-solid","horizonal-scroll","horizonal-scroll-solid","horizontal-menu-circle","horizontal-menu-circle-remix","horizontal-menu-circle-solid","horizontal-slider-square","horizontal-slider-square-remix","horizontal-slider-square-solid","hospital-sign-square","hospital-sign-square-remix","hospital-sign-square-solid","hot-air-balloon","hot-air-balloon-remix","hot-air-balloon-solid","hot-spring","hot-spring-solid","hotel-bed-5","hotel-bed-5-remix","hotel-bed-5-solid","hotel-five-star","hotel-five-star-remix","hotel-five-star-solid","hourglass","hourglass-remix","hourglass-solid","html-five","html-five-remix","html-five-solid","ice-cream-2","ice-cream-2-remix","ice-cream-2-solid","image-saturation","image-saturation-solid","image-saturation-vertical-remix","inbox-content","inbox-content-remix","inbox-content-solid","inbox-post","inbox-post-remix","inbox-post-solid","incognito-mode","incognito-mode-remix","incognito-mode-solid","industry-innovation-and-infrastructure","industry-innovation-and-infrastructure-remix","industry-innovation-and-infrastructure-solid","information-circle","information-circle-remix","information-circle-solid","information-desk","information-desk-remix","information-desk-solid","input-box","input-box-remix","input-box-solid","insert-column","insert-column-remix","insert-column-solid","insert-side","insert-side-remix","insert-side-solid","insurance-hand","insurance-hand-remix","insurance-hand-solid","intellectual","intellectual-remix","intellectual-solid","intersex-symbol","intersex-symbol-remix","intersex-symbol-solid","invisible-1","invisible-1-remix","invisible-1-solid","invisible-2","invisible-2-remix","invisible-2-solid","ios-ipados","ios-ipados-remix","ios-ipados-solid","ipad-tablet-screen","ipad-tablet-screen-remix","ipad-tablet-screen-solid","iris-scan","iris-scan-remix","iris-scan-solid","justice-scale-2","justice-scale-2-remix","justice-scale-2-solid","keyboard","keyboard-remix","keyboard-solid","keyhole-lock-circle","keyhole-lock-circle-remix","keyhole-lock-circle-solid","ladder","ladder-remix","ladder-solid","landing","landing-remix","landing-solid","landscape-view","landscape-view-remix","landscape-view-solid","laptop","laptop-remix","laptop-solid","layer-mask","layer-mask-remix","layer-mask-solid","layers-1","layers-1-remix","layers-1-solid","layout-right-sidebar","layout-right-sidebar-remix","layout-right-sidebar-solid","layout-window-4","layout-window-4-remix","layout-window-4-solid","leaf-protect","leaf-protect-remix","leaf-protect-solid","lens","lens-remix","lens-solid","lift","lift-remix","lift-solid","lightbulb","lightbulb-remix","lightbulb-solid","lightning-cloud","lightning-cloud-remix","lightning-cloud-solid","like-1","like-1-remix","like-1-solid","line-arrow-expand-horizontal-remix","line-arrow-right-circle-2-remix","line-arrow-transfer-horizontal-square-1-remix","link-chain","link-chain-remix","link-chain-solid","lipstick","lipstick-remix","lipstick-solid","loading-circle","loading-circle-remix","loading-circle-solid","loading-horizontal-2","loading-horizontal-2-remix","loading-horizontal-2-solid","location-heart-pin","location-heart-pin-remix","location-heart-pin-solid","location-pin","location-pin-3","location-pin-3-remix","location-pin-3-solid","location-pin-disabled","location-pin-disabled-remix","location-pin-disabled-solid","location-pin-remix","location-pin-solid","lock-comment-security","lock-comment-security-solid","log","log-remix","log-solid","login-1","login-1-remix","login-1-solid","lost-and-found","lost-and-found-remix","lost-and-found-solid","magic-wand-1","magic-wand-1-remix","magic-wand-1-solid","magnet","magnet-remix","magnet-solid","mail-notification","mail-notification-remix","mail-notification-solid","mail-outgoing","mail-outgoing-remix","mail-outgoing-solid","mail-search","mail-search-remix","mail-search-solid","mail-send","mail-send-email-message","mail-send-email-message-remix","mail-send-email-message-solid","mail-send-remix","mail-send-reply-all","mail-send-reply-all-remix","mail-send-reply-all-solid","mail-send-solid","mail-setting","mail-setting-gear-remix","mail-setting-solid","mall","mall-remix","mall-solid","man-arm-raises-2-alternate","man-arm-raises-2-alternate-remix","man-arm-raises-2-alternate-solid","map-fold","map-fold-remix","map-fold-solid","map-location-star-pin","map-location-star-pin-remix","map-location-star-pin-solid","maximize-1","maximize-1-remix","maximize-1-solid","medical-bag","medical-bag-remix","medical-bag-solid","megaphone-refresh","megaphone-refresh-remix","megaphone-refresh-solid","memes-comment-reply","memes-comment-reply-remix","memes-comment-reply-solid","microscope-observation-sciene","microscope-observation-sciene-remix","microscope-observation-sciene-solid","module","module-remix","module-solid","money-cash-bill-1","money-cash-bill-1-solid","moon-stars","moon-stars-remix","moon-stars-solid","mouse-wireless","mouse-wireless-1","mouse-wireless-1-remix","mouse-wireless-1-solid","mouse-wireless-remix","mouse-wireless-solid","moustache","moustache-remix","moustache-solid","multiple-file-1","multiple-file-1-remix","multiple-file-1-solid","multiple-stars","multiple-stars-remix","multiple-stars-solid","music-note-2","music-note-2-remix","music-note-2-solid","music-note-trebble-clef","music-note-trebble-clef-remix","music-note-trebble-clef-solid","navigation-arrow-off","navigation-arrow-off-remix","navigation-arrow-off-solid","new-folder","new-folder-remix","new-folder-solid","news-paper","news-paper-remix","news-paper-solid","nintendo-xbox-controller-1","nintendo-xbox-controller-1-remix","nintendo-xbox-controller-1-solid","no-photo-taking-zone","no-photo-taking-zone-remix","no-photo-taking-zone-solid","no-poverty","no-poverty-remix","no-poverty-solid","no-smaking-area","no-smaking-area-remix","no-smaking-area-solid","no-touch-sign","no-touch-sign-remix","no-touch-sign-solid","notepad-text","notepad-text-solid","notification-alarm-snooze","notification-alarm-snooze-remix","notification-alarm-snooze-solid","notification-alert","notification-alert-remix","notification-alert-solid","octagram-shape","octagram-shape-remix","octagram-shape-solid","office-worker","office-worker-remix","office-worker-solid","ok-hand","ok-hand-remix","ok-hand-solid","one-finger-tap","one-finger-tap-remix","one-finger-tap-solid","one-handed-holding-tablet-handheld","one-handed-holding-tablet-handheld-remix","one-handed-holding-tablet-handheld-solid","open-umbrella","open-umbrella-remix","open-umbrella-solid","pacman","pacman-remix","pacman-solid","padlock-key","padlock-key-remix","padlock-key-solid","padlock-square-2","padlock-square-2-remix","padlock-square-2-solid","page-setting","page-setting-remix","page-setting-solid","paint-bucket","paint-bucket-remix","paint-bucket-solid","paint-palette","paint-palette-remix","paint-palette-solid","paintbrush-2","paintbrush-2-remix","paintbrush-2-solid","painting-board","painting-board-remix","painting-board-solid","panoramic-screen","panoramic-screen-remix","panoramic-screen-solid","parachute-drop","parachute-drop-remix","parachute-drop-solid","park","park-remix","park-solid","password-lock","password-lock-remix","password-lock-solid","pathfinder-outline","pathfinder-outline-solid","pathfinder-square-divide-remix","payment-recieve-7","payment-recieve-7-remix","payment-recieve-7-solid","pen-1","pen-1-remix","pen-1-solid","pen-tool","pen-tool-remix","pen-tool-solid","pencil-circle","pencil-circle-remix","pencil-circle-solid","pencil-square","pencil-square-remix","pencil-square-solid","pet-paw","pet-paw-remix","pet-paw-solid","pharmacy","pharmacy-remix","pharmacy-solid","phone","phone-remix","phone-solid","phone-vibrate","phone-vibrate-remix","phone-vibrate-solid","piggy-bank","piggy-bank-remix","piggy-bank-solid","pin-2","pin-2-remix","pin-2-solid","pinwheel","pinwheel-remix","pinwheel-solid","play-list-1","play-list-1-remix","play-list-1-solid","play-list-folder","play-list-folder-remix","play-list-folder-solid","polaroid","polaroid-remix","polaroid-solid","politics-vote-2","politics-vote-2-remix","politics-vote-2-solid","pool-ladder","pool-ladder-remix","pool-ladder-solid","pork-meat","pork-meat-remix","pork-meat-solid","potted-flower","potted-flower-remix","potted-flower-solid","pound-circle","pound-circle-remix","pound-circle-solid","presentation","presentation-remix","presentation-solid","printer","printer-remix","printer-solid","production-belt","production-belt-remix","production-belt-solid","projector-screen","projector-screen-remix","projector-screen-solid","pyramid-shape","pyramid-shape-remix","pyramid-shape-solid","quotation-2","quotation-2-remix","quotation-2-solid","radioactive-1","radioactive-1-remix","radioactive-1-solid","receipt-cross","receipt-cross-remix","receipt-cross-solid","recording-tape-1","recording-tape-1-remix","recording-tape-1-solid","rectangle-flag","rectangle-flag-remix","rectangle-flag-solid","recycle-1","recycle-1-remix","recycle-1-solid","recycle-bin","recycle-bin-2","recycle-bin-2-remix","recycle-bin-2-solid","recycle-bin-3","recycle-bin-3-remix","recycle-bin-3-solid","recycle-bin-remix","recycle-bin-solid","reduced-inequalities","reduced-inequalities-remix","reduced-inequalities-solid","refrigerator","refrigerator-remix","refrigerator-solid","reply-to-message-typing","reply-to-message-typing-remix","reply-to-message-typing-solid","reset-clock","reset-clock-remix","reset-clock-solid","return-3","return-3-remix","return-3-solid","ringing-bell-notification","ringing-bell-notification-remix","ringing-bell-notification-solid","rotate-left","rotate-left-1-remix","rotate-left-solid","round-anchor-point","round-anchor-point-remix","round-anchor-point-solid","rss-square","rss-square-remix","rss-square-solid","ruler","ruler-remix","ruler-solid","sad-face","sad-face-remix","sad-face-solid","safari","safari-logo-remix","safari-solid","safe-vault","safe-vault-remix","safe-vault-solid","sail-ship","sail-ship-remix","sail-ship-solid","scissors","scissors-remix","scissors-solid","screen-1","screen-1-remix","screen-1-solid","screwdriver","screwdriver-remix","screwdriver-solid","script-2","script-2-remix","script-2-solid","sd-card","sd-card-remix","sd-card-solid","search-visual","search-visual-remix","search-visual-solid","select-all","select-all-remix","select-all-solid","select-circle-area-1","select-circle-area-1-remix","select-circle-area-1-solid","share-link","share-link-remix","share-link-solid","share-lock","share-lock-remix","share-lock-solid","shield-1","shield-1-remix","shield-1-solid","shipment-upload","shipment-upload-remix","shipment-upload-solid","shipping-box-1","shipping-box-1-remix","shipping-box-1-solid","shopping-basket-1","shopping-basket-1-remix","shopping-basket-1-solid","shopping-cart-add","shopping-cart-add-remix","shopping-cart-add-solid","shuffle","shuffle-remix","shuffle-solid","sign-at","sign-at-remix","sign-at-solid","signal-full","signal-full-remix","signal-full-solid","sizing","sizing-remix","sizing-solid","skull-2","skull-2-remix","skull-2-solid","slack","slack-logo-remix","slack-solid","smiley-drool","smiley-drool-remix","smiley-drool-solid","smiley-indiferent","smiley-indiferent-remix","smiley-indiferent-solid","smiley-laughing-1","smiley-laughing-1-remix","smiley-laughing-1-solid","smiley-sparks","smiley-sparks-remix","smiley-sparks-solid","smoking-area","smoking-area-remix","smoking-area-solid","sofa","sofa-remix","sofa-solid","speaker-2","speaker-2-remix","speaker-2-solid","spiral-shape","spiral-shape-remix","spiral-shape-solid","spotify","spotify-logo-remix","spotify-solid","stamp","stamp-remix","stamp-solid","star-circle","star-circle-remix","star-circle-solid","star-medal","star-medal-1-remix","star-medal-solid","steps-1","steps-1-remix","steps-1-solid","stock","stock-remix","stock-solid","stool","stool-remix","stool-solid","stopwatch-half","stopwatch-half-remix","stopwatch-half-solid","store-1-remix","store-2","store-2-solid","strawberry","strawberry-remix","strawberry-solid","street-sign","street-sign-remix","street-sign-solid","stroller","stroller-remix","stroller-solid","suitcase-rolling","suitcase-rolling-remix","suitcase-rolling-solid","sun","sun-remix","sun-solid","sunset","sunset-remix","sunset-solid","synchronize","synchronize-solid","table","table-remix","table-solid","tablet-capsule","tablet-capsule-remix","tablet-capsule-solid","tag-alt","tag-alt-remix","tag-alt-solid","tailless-line-arrow-horizonal-scroll-remix","tailless-line-arrow-right-circle-remix","tailless-line-arrow-up-2-remix","target-3","target-3-remix","target-3-solid","task-list-edit","task-list-edit-remix","task-list-edit-solid","telescope","telescope-remix","telescope-solid","test-tube","test-tube-remix","test-tube-solid","text-box-1","text-box-1-remix","text-box-1-solid","text-image-center-large","text-image-center-large-remix","text-image-center-large-solid","text-shadow","text-shadow-remix","text-shadow-solid","theater-mask","theater-mask-remix","theater-mask-solid","thermometer","thermometer-remix","thermometer-solid","threat-phone","threat-phone-remix","threat-phone-solid","ticket-1","ticket-1-remix","ticket-1-solid","tiktok","tiktok-logo-remix","tiktok-solid","toast","toast-remix","toast-solid","toilet-man","toilet-man-remix","toilet-man-solid","toilet-sign-man","toilet-sign-man-remix","toilet-sign-man-solid","toilet-women","toilet-women-remix","toilet-women-solid","tool-box","tool-box-remix","tool-box-solid","top-order-report","top-order-report-remix","top-order-report-solid","traffic-light","traffic-light-remix","traffic-light-solid","transparent","transparent-remix","transparent-solid","travel-places-hot-spring-remix","treasure-chest","treasure-chest-remix","treasure-chest-solid","tree-1","tree-1-remix","tree-1-solid","trending-content","trending-content-remix","trending-content-solid","triangle-arrow-curvy-both-direction-2-remix","triangle-arrow-expand-remix","triangle-arrow-roadmap-remix","triangle-arrow-synchronize-2-remix","triangle-arrow-turn-down-left-large-remix","tune-adjust-volume","tune-adjust-volume-remix","tune-adjust-volume-solid","upload-box-1","upload-box-1-solid","usb-port","usb-port-remix","usb-port-solid","user-face-id-mask","user-face-id-mask-remix","user-face-id-mask-solid","user-face-male","user-face-male-remix","user-face-male-solid","user-feedback-heart","user-feedback-heart-remix","user-feedback-heart-solid","user-multiple-accounts","user-multiple-accounts-remix","user-multiple-accounts-solid","user-pin","user-pin-remix","user-pin-solid","user-podcast","user-podcast-remix","user-podcast-solid","user-protection-1-remix","user-protection-check","user-protection-check-solid","user-single-neutral-male","user-single-neutral-male-remix","user-single-neutral-male-solid","user-sticker-square","user-sticker-square-remix","user-sticker-square-solid","user-switch-account","user-switch-account-remix","user-switch-account-solid","video-close-captioning","video-close-captioning-remix","video-close-captioning-solid","video-subtitles","video-subtitles-remix","video-subtitles-solid","virtual-reality","virtual-reality-remix","virtual-reality-solid","virus-antivirus","virus-antivirus-remix","virus-antivirus-solid","visual-blind","visual-blind-remix","visual-blind-solid","voice-activation-1","voice-activation-1-remix","voice-activation-1-solid","voice-mail","voice-mail-remix","voice-mail-solid","voice-scan-1","voice-scan-1-remix","voice-scan-1-solid","voice-typing-word-convert","voice-typing-word-convert-remix","voice-typing-word-convert-solid","volume-level-high","volume-level-high-remix","volume-level-high-solid","vpn-connection","vpn-connection-remix","vpn-connection-solid","wallet","wallet-remix","wallet-solid","warehouse-1","warehouse-1-remix","warehouse-1-solid","warning-diamond","warning-diamond-remix","warning-diamond-solid","warp-squeeze","warp-squeeze-remix","warp-squeeze-solid","watch-1","watch-1-remix","watch-1-solid","watch-circle-menu","watch-circle-menu-remix","watch-circle-menu-solid","water-melon","water-melon-remix","water-melon-solid","wave-signal-square","wave-signal-square-remix","wave-signal-square-solid","waving-hand","waving-hand-remix","waving-hand-solid","web","web-remix","web-solid","webcam-off","webcam-off-remix","webcam-off-solid","webcam-video","webcam-video-remix","webcam-video-solid","wheat","wheat-solid","wheelchair-2","wheelchair-2-remix","wheelchair-2-solid","widget","widget-remix","widget-solid","wifi","wifi-signal-full-remix","wifi-solid","wine","wine-remix","wine-solid","workspace-desk","workspace-desk-remix","workspace-desk-solid","world","world-remix","world-solid","wrap-arch","wrap-arch-remix","wrap-arch-solid","wrench-circle","wrench-circle-remix","wrench-circle-solid","yin-yang-symbol","yin-yang-symbol-remix","yin-yang-symbol-solid","zoom-in","zoom-in-gesture","zoom-in-gesture-remix","zoom-in-gesture-solid","zoom-in-remix","zoom-in-solid"],"categories":{"ArtificialIntelligence":["ai-edit-robot","ai-edit-robot-remix","ai-edit-robot-solid","ai-generate-portrait-image-spark","ai-generate-portrait-image-spark-remix","ai-generate-portrait-image-spark-solid","ai-generate-variation-spark","ai-generate-variation-spark-remix","ai-generate-variation-spark-solid","ai-generate-voice-robot-2","ai-generate-voice-robot-2-remix","ai-generate-voice-robot-2-solid","ai-science-robot","ai-science-robot-remix","ai-science-robot-solid","ai-technology-spark","ai-technology-spark-remix","ai-technology-spark-solid","deepfake-technology-1","deepfake-technology-1-remix","deepfake-technology-1-solid"],"ComputerDevices":["battery-charging","battery-charging-remix","battery-charging-solid","battery-low-1-remix","battery-low-3","battery-low-3-solid","bluetooth","bluetooth-remix","bluetooth-solid","cable-split","cable-split-remix","cable-split-solid","change-background-transparent","change-background-transparent-remix","change-background-transparent-solid","charging","charging-remix","charging-solid","command","command-remix","command-solid","computer-pc-desktop","computer-pc-desktop-remix","computer-pc-desktop-solid","controller-1","controller-1-remix","controller-1-solid","cyborg-2","cyborg-2-remix","cyborg-2-solid","database","database-remix","database-server-3","database-server-3-remix","database-server-3-solid","database-solid","delete-keyboard","delete-keyboard-remix","delete-keyboard-solid","desktop-lock","desktop-lock-remix","desktop-lock-solid","device-database-encryption-1","device-database-encryption-1-remix","device-database-encryption-1-solid","dropbox","dropbox-logo-remix","dropbox-solid","electric-cord-1","electric-cord-1-remix","electric-cord-1-solid","facebook-1","facebook-1-solid","facebook-logo-1-remix","floppy-disk","floppy-disk-remix","floppy-disk-solid","hand-held","hand-held-remix","hand-held-solid","hard-drive-2","hard-drive-2-remix","hard-drive-2-solid","ios-ipados","ios-ipados-remix","ios-ipados-solid","ipad-tablet-screen","ipad-tablet-screen-remix","ipad-tablet-screen-solid","keyboard","keyboard-remix","keyboard-solid","laptop","laptop-remix","laptop-solid","mouse-wireless","mouse-wireless-1","mouse-wireless-1-remix","mouse-wireless-1-solid","mouse-wireless-remix","mouse-wireless-solid","one-handed-holding-tablet-handheld","one-handed-holding-tablet-handheld-remix","one-handed-holding-tablet-handheld-solid","printer","printer-remix","printer-solid","return-3","return-3-remix","return-3-solid","safari","safari-logo-remix","safari-solid","screen-1","screen-1-remix","screen-1-solid","sd-card","sd-card-remix","sd-card-solid","slack","slack-logo-remix","slack-solid","spotify","spotify-logo-remix","spotify-solid","tiktok","tiktok-logo-remix","tiktok-solid","usb-port","usb-port-remix","usb-port-solid","virtual-reality","virtual-reality-remix","virtual-reality-solid","voice-mail","voice-mail-remix","voice-mail-solid","vpn-connection","vpn-connection-remix","vpn-connection-solid","watch-1","watch-1-remix","watch-1-solid","watch-circle-menu","watch-circle-menu-remix","watch-circle-menu-solid","webcam-off","webcam-off-remix","webcam-off-solid","webcam-video","webcam-video-remix","webcam-video-solid","wifi","wifi-signal-full-remix","wifi-solid"],"Culture":["cao-dai","cao-dai-remix","cao-dai-solid","news-paper","news-paper-remix","news-paper-solid","politics-vote-2","politics-vote-2-remix","politics-vote-2-solid","ticket-1","ticket-1-remix","ticket-1-solid","yin-yang-symbol","yin-yang-symbol-remix","yin-yang-symbol-solid"],"Entertainment":["balloon","balloon-remix","balloon-solid","button-play-circle","button-play-circle-remix","button-play-circle-solid","button-power-1","button-power-1-remix","button-power-1-solid","camera-video","camera-video-remix","camera-video-solid","card-game-diamond","card-game-diamond-remix","card-game-diamond-solid","chess-pawn","chess-pawn-remix","chess-pawn-solid","dices-entertainment-gaming-dices","dices-entertainment-gaming-dices-remix","dices-entertainment-gaming-dices-solid","earpods","earpods-remix","earpods-solid","gameboy","gameboy-remix","gameboy-solid","music-note-2","music-note-2-remix","music-note-2-solid","music-note-trebble-clef","music-note-trebble-clef-remix","music-note-trebble-clef-solid","nintendo-xbox-controller-1","nintendo-xbox-controller-1-remix","nintendo-xbox-controller-1-solid","pacman","pacman-remix","pacman-solid","play-list-1","play-list-1-remix","play-list-1-solid","play-list-folder","play-list-folder-remix","play-list-folder-solid","recording-tape-1","recording-tape-1-remix","recording-tape-1-solid","speaker-2","speaker-2-remix","speaker-2-solid","tune-adjust-volume","tune-adjust-volume-remix","tune-adjust-volume-solid","volume-level-high","volume-level-high-remix","volume-level-high-solid"],"FoodDrink":["allergens-fish-remix","allergens-gluten-remix","beer-pitch","beer-pitch-remix","beer-pitch-solid","bowl-chop-stick","bowl-chop-stick-remix","bowl-chop-stick-solid","burger","burger-remix","burger-solid","cake-slice","cake-slice-remix","cake-slice-solid","cheese","cheese-remix","cheese-solid","chef-toque-hat","chef-toque-hat-remix","chef-toque-hat-solid","cherries","cherries-remix","cherries-solid","coffee-bean","coffee-bean-remix","coffee-bean-solid","coffee-mug","coffee-mug-remix","coffee-mug-solid","drum-stick","drum-stick-remix","drum-stick-solid","fish","fish-solid","food-truck-event-fair","food-truck-event-fair-remix","food-truck-event-fair-solid","fork-knife","fork-knife-remix","fork-knife-solid","fork-plate","fork-plate-remix","fork-plate-solid","fried-egg-breakfast","fried-egg-breakfast-remix","fried-egg-breakfast-solid","ice-cream-2","ice-cream-2-remix","ice-cream-2-solid","pork-meat","pork-meat-remix","pork-meat-solid","refrigerator","refrigerator-remix","refrigerator-solid","strawberry","strawberry-remix","strawberry-solid","toast","toast-remix","toast-solid","water-melon","water-melon-remix","water-melon-solid","wheat","wheat-solid","wine","wine-remix","wine-solid"],"Health":["call-center-support-service","call-center-support-service-remix","call-center-support-service-solid","ear-speciality","ear-speciality-remix","ear-speciality-solid","eye-optic","eye-optic-remix","eye-optic-solid","heart-rate-pulse-graph","heart-rate-pulse-graph-remix","heart-rate-pulse-graph-solid","hospital-sign-square","hospital-sign-square-remix","hospital-sign-square-solid","insurance-hand","insurance-hand-remix","insurance-hand-solid","medical-bag","medical-bag-remix","medical-bag-solid","microscope-observation-sciene","microscope-observation-sciene-remix","microscope-observation-sciene-solid","pharmacy","pharmacy-remix","pharmacy-solid","tablet-capsule","tablet-capsule-remix","tablet-capsule-solid","virus-antivirus","virus-antivirus-remix","virus-antivirus-solid"],"ImagesPhotography":["auto-flash","auto-flash-remix","auto-flash-solid","camera-1","camera-1-remix","camera-1-solid","film-slate","film-slate-remix","film-slate-solid","flash-1","flash-1-remix","flash-1-solid","focus-points","focus-points-remix","focus-points-solid","gallery-2","gallery-2-remix","gallery-2-solid","landscape-view","landscape-view-remix","landscape-view-solid","lens","lens-remix","lens-solid","polaroid","polaroid-remix","polaroid-solid"],"InterfaceEssential":["3d-coordinate-axis","3d-coordinate-axis-remix","3d-coordinate-axis-solid","add-bell-notification","add-bell-notification-remix","add-bell-notification-solid","add-layer-2","add-layer-2-remix","add-layer-2-solid","align-object-left","align-object-left-remix","align-object-left-solid","align-right","align-right-1-remix","align-right-solid","align-selection","align-selection-remix","align-selection-solid","ampersand","ampersand-remix","ampersand-solid","archive-box","archive-box-remix","archive-box-solid","arrow-cursor-1","arrow-cursor-1-remix","arrow-cursor-1-solid","arrow-cursor-move","arrow-cursor-move-remix","arrow-cursor-move-solid","arrow-curvy-both-direction-2","arrow-curvy-both-direction-2-solid","arrow-diagonal-2","arrow-diagonal-2-solid","arrow-expand","arrow-expand-solid","arrow-right-circle-1","arrow-right-circle-1-solid","arrow-right-circle-2","arrow-right-circle-2-solid","arrow-roadmap","arrow-roadmap-solid","arrow-transfer-horizontal-square","arrow-transfer-horizontal-square-solid","arrow-turn-down-large","arrow-turn-down-large-solid","arrow-up-4","arrow-up-4-solid","ascending-alphabetical-order","ascending-alphabetical-order-remix","ascending-alphabetical-order-solid","attribution","attribution-remix","attribution-solid","binoculars","binoculars-remix","binoculars-solid","block-1","block-1-remix","block-1-solid","bomb","bomb-remix","bomb-solid","book-1","book-1-remix","book-1-solid","bookmark","bookmark-1-remix","bookmark-solid","border-frame","border-frame-remix","border-frame-solid","broken-link-2","broken-link-2-remix","broken-link-2-solid","calendar-add","calendar-add-remix","calendar-add-solid","calendar-check","calendar-check-remix","calendar-check-solid","calendar-heart","calendar-heart-remix","calendar-heart-solid","calendar-mark","calendar-mark-remix","calendar-mark-solid","calendar-note-remix","candle","candle-remix","candle-solid","chat-bubble-square-question-remix","check-thick","check-thick-remix","check-thick-solid","circle-and-square-shape","circle-and-square-shape-remix","circle-and-square-shape-solid","circle-clock","circle-clock-remix","circle-clock-solid","clean-broom-wipe","clean-broom-wipe-remix","clean-broom-wipe-solid","cleaning-room-woman","cleaning-room-woman-remix","cleaning-room-woman-solid","cog","cog-1-remix","cog-automation","cog-automation-remix","cog-automation-solid","cog-solid","color-picker","color-picker-remix","color-picker-solid","compass-navigator","compass-navigator-remix","compass-navigator-solid","compress-pdf","compress-pdf-remix","compress-pdf-solid","content-statistic","content-statistic-remix","content-statistic-solid","convert-pdf-1","convert-pdf-1-remix","convert-pdf-1-solid","creative-commons","creative-commons-remix","creative-commons-solid","crop-selection","crop-selection-remix","crop-selection-solid","customer-support-3","customer-support-3-remix","customer-support-3-solid","customer-support-7","customer-support-7-remix","customer-support-7-solid","cut","cut-remix","cut-solid","dark-dislay-mode","dark-dislay-mode-remix","dark-dislay-mode-solid","dashboard-1","dashboard-1-remix","dashboard-1-solid","dashboard-gauge-2","dashboard-gauge-2-solid","dashboard-gauge-medium-2-remix","delete-bookmark","delete-bookmark-remix","delete-bookmark-solid","delete-row","delete-row-remix","delete-row-solid","description","description-remix","description-solid","diagonal-triangle-arrow-2-remix","dial-pad-finger-2","dial-pad-finger-2-remix","dial-pad-finger-2-solid","disable-alarm","disable-alarm-remix","disable-alarm-solid","disable-heart","disable-heart-remix","disable-heart-solid","disable-protection","disable-protection-remix","disable-protection-solid","division-circle","division-circle-remix","division-circle-solid","door","door-remix","door-solid","download-box-2","download-box-2-remix","download-box-2-solid","dumbell","dumbell-remix","dumbell-solid","empty-clipboard","empty-clipboard-remix","empty-clipboard-solid","end-point-branches","end-point-branches-remix","end-point-branches-solid","end-point-diamond","end-point-diamond-remix","end-point-diamond-solid","eraser","eraser-remix","eraser-solid","exit-full-screen","exit-full-screen-remix","exit-full-screen-solid","expand-horizontal-2","expand-horizontal-2-solid","fahrenheit","fahrenheit-remix","fahrenheit-solid","feather-pen","feather-pen-remix","feather-pen-solid","file-check-alternate","file-check-alternate-remix","file-check-alternate-solid","file-folder","file-folder-remix","file-folder-solid","file-report","file-report-remix","file-report-solid","file-search","file-search-remix","file-search-solid","fill-and-sign","fill-and-sign-remix","fill-and-sign-solid","filter-1","filter-1-remix","filter-1-solid","fingerprint-2","fingerprint-2-remix","fingerprint-2-solid","firefighter-truck","firefighter-truck-remix","firefighter-truck-solid","fit-height","fit-height-remix","fit-height-solid","fit-to-width-square","fit-to-width-square-solid","fit-width-remix","flashlight","flashlight-remix","flashlight-solid","flip-horizontal-circle-1","flip-horizontal-circle-1-remix","flip-horizontal-circle-1-solid","give-gift","give-gift-remix","give-gift-solid","graphic-template-website-ui","graphic-template-website-ui-remix","graphic-template-website-ui-solid","half-star-2","half-star-2-remix","half-star-2-solid","heater","heater-remix","heater-solid","help-chat-1","help-chat-1-solid","hierarchy-1","hierarchy-1-remix","hierarchy-1-solid","hierarchy-15","hierarchy-15-remix","hierarchy-15-solid","home-1","home-1-remix","home-1-solid","horizonal-scroll","horizonal-scroll-solid","horizontal-menu-circle","horizontal-menu-circle-remix","horizontal-menu-circle-solid","horizontal-slider-square","horizontal-slider-square-remix","horizontal-slider-square-solid","hourglass","hourglass-remix","hourglass-solid","image-saturation","image-saturation-solid","image-saturation-vertical-remix","information-circle","information-circle-remix","information-circle-solid","input-box","input-box-remix","input-box-solid","insert-column","insert-column-remix","insert-column-solid","insert-side","insert-side-remix","insert-side-solid","invisible-1","invisible-1-remix","invisible-1-solid","invisible-2","invisible-2-remix","invisible-2-solid","iris-scan","iris-scan-remix","iris-scan-solid","keyhole-lock-circle","keyhole-lock-circle-remix","keyhole-lock-circle-solid","ladder","ladder-remix","ladder-solid","layer-mask","layer-mask-remix","layer-mask-solid","layers-1","layers-1-remix","layers-1-solid","layout-right-sidebar","layout-right-sidebar-remix","layout-right-sidebar-solid","layout-window-4","layout-window-4-remix","layout-window-4-solid","lightbulb","lightbulb-remix","lightbulb-solid","lightning-cloud","lightning-cloud-remix","lightning-cloud-solid","like-1","like-1-remix","like-1-solid","line-arrow-expand-horizontal-remix","line-arrow-right-circle-2-remix","line-arrow-transfer-horizontal-square-1-remix","link-chain","link-chain-remix","link-chain-solid","loading-circle","loading-circle-remix","loading-circle-solid","loading-horizontal-2","loading-horizontal-2-remix","loading-horizontal-2-solid","login-1","login-1-remix","login-1-solid","magic-wand-1","magic-wand-1-remix","magic-wand-1-solid","magnet","magnet-remix","magnet-solid","maximize-1","maximize-1-remix","maximize-1-solid","megaphone-refresh","megaphone-refresh-remix","megaphone-refresh-solid","memes-comment-reply","memes-comment-reply-remix","memes-comment-reply-solid","moon-stars","moon-stars-remix","moon-stars-solid","multiple-file-1","multiple-file-1-remix","multiple-file-1-solid","multiple-stars","multiple-stars-remix","multiple-stars-solid","new-folder","new-folder-remix","new-folder-solid","no-photo-taking-zone","no-photo-taking-zone-remix","no-photo-taking-zone-solid","no-touch-sign","no-touch-sign-remix","no-touch-sign-solid","notepad-text","notepad-text-solid","octagram-shape","octagram-shape-remix","octagram-shape-solid","ok-hand","ok-hand-remix","ok-hand-solid","one-finger-tap","one-finger-tap-remix","one-finger-tap-solid","open-umbrella","open-umbrella-remix","open-umbrella-solid","padlock-key","padlock-key-remix","padlock-key-solid","padlock-square-2","padlock-square-2-remix","padlock-square-2-solid","page-setting","page-setting-remix","page-setting-solid","paint-bucket","paint-bucket-remix","paint-bucket-solid","paint-palette","paint-palette-remix","paint-palette-solid","paintbrush-2","paintbrush-2-remix","paintbrush-2-solid","panoramic-screen","panoramic-screen-remix","panoramic-screen-solid","password-lock","password-lock-remix","password-lock-solid","pathfinder-outline","pathfinder-outline-solid","pathfinder-square-divide-remix","pen-1","pen-1-remix","pen-1-solid","pen-tool","pen-tool-remix","pen-tool-solid","pencil-circle","pencil-circle-remix","pencil-circle-solid","pencil-square","pencil-square-remix","pencil-square-solid","pin-2","pin-2-remix","pin-2-solid","pinwheel","pinwheel-remix","pinwheel-solid","presentation","presentation-remix","presentation-solid","projector-screen","projector-screen-remix","projector-screen-solid","pyramid-shape","pyramid-shape-remix","pyramid-shape-solid","quotation-2","quotation-2-remix","quotation-2-solid","radioactive-1","radioactive-1-remix","radioactive-1-solid","recycle-bin-2","recycle-bin-2-remix","recycle-bin-2-solid","recycle-bin-3","recycle-bin-3-remix","recycle-bin-3-solid","reset-clock","reset-clock-remix","reset-clock-solid","ringing-bell-notification","ringing-bell-notification-remix","ringing-bell-notification-solid","rotate-left","rotate-left-1-remix","rotate-left-solid","round-anchor-point","round-anchor-point-remix","round-anchor-point-solid","ruler","ruler-remix","ruler-solid","scissors","scissors-remix","scissors-solid","screwdriver","screwdriver-remix","screwdriver-solid","search-visual","search-visual-remix","search-visual-solid","select-all","select-all-remix","select-all-solid","select-circle-area-1","select-circle-area-1-remix","select-circle-area-1-solid","share-link","share-link-remix","share-link-solid","share-lock","share-lock-remix","share-lock-solid","shield-1","shield-1-remix","shield-1-solid","shipment-upload-remix","shuffle","shuffle-remix","shuffle-solid","sizing","sizing-remix","sizing-solid","skull-2","skull-2-remix","skull-2-solid","spiral-shape","spiral-shape-remix","spiral-shape-solid","stamp","stamp-remix","stamp-solid","star-circle","star-circle-remix","star-circle-solid","star-medal","star-medal-1-remix","star-medal-solid","stopwatch-half","stopwatch-half-remix","stopwatch-half-solid","sun","sun-remix","sun-solid","synchronize","synchronize-solid","table","table-remix","table-solid","tailless-line-arrow-horizonal-scroll-remix","tailless-line-arrow-right-circle-remix","tailless-line-arrow-up-2-remix","text-box-1","text-box-1-remix","text-box-1-solid","text-image-center-large","text-image-center-large-remix","text-image-center-large-solid","text-shadow","text-shadow-remix","text-shadow-solid","thermometer","thermometer-remix","thermometer-solid","tool-box","tool-box-remix","tool-box-solid","top-order-report","top-order-report-remix","top-order-report-solid","transparent","transparent-remix","transparent-solid","trending-content","trending-content-remix","trending-content-solid","triangle-arrow-curvy-both-direction-2-remix","triangle-arrow-expand-remix","triangle-arrow-roadmap-remix","triangle-arrow-synchronize-2-remix","triangle-arrow-turn-down-left-large-remix","upload-box-1","upload-box-1-solid","user-face-id-mask","user-face-id-mask-remix","user-face-id-mask-solid","user-face-male","user-face-male-remix","user-face-male-solid","user-feedback-heart","user-feedback-heart-remix","user-feedback-heart-solid","user-multiple-accounts","user-multiple-accounts-remix","user-multiple-accounts-solid","user-podcast","user-podcast-remix","user-podcast-solid","user-protection-1-remix","user-protection-check","user-protection-check-solid","user-single-neutral-male","user-single-neutral-male-remix","user-single-neutral-male-solid","user-sticker-square","user-sticker-square-remix","user-sticker-square-solid","user-switch-account","user-switch-account-remix","user-switch-account-solid","video-close-captioning","video-close-captioning-remix","video-close-captioning-solid","video-subtitles","video-subtitles-remix","video-subtitles-solid","voice-activation-1","voice-activation-1-remix","voice-activation-1-solid","voice-scan-1","voice-scan-1-remix","voice-scan-1-solid","voice-typing-word-convert","voice-typing-word-convert-remix","voice-typing-word-convert-solid","warning-diamond","warning-diamond-remix","warning-diamond-solid","warp-squeeze","warp-squeeze-remix","warp-squeeze-solid","wave-signal-square","wave-signal-square-remix","wave-signal-square-solid","waving-hand","waving-hand-remix","waving-hand-solid","wrap-arch","wrap-arch-remix","wrap-arch-solid","wrench-circle","wrench-circle-remix","wrench-circle-solid","zoom-in","zoom-in-gesture","zoom-in-gesture-remix","zoom-in-gesture-solid","zoom-in-remix","zoom-in-solid"],"Mail":["chat-bubble-oval-notification","chat-bubble-oval-notification-remix","chat-bubble-oval-notification-solid","chat-bubble-oval-smiley-1","chat-bubble-oval-smiley-1-remix","chat-bubble-oval-smiley-1-solid","chat-bubble-square-lock-remix","chat-bubble-square-warning","chat-bubble-square-warning-remix","chat-bubble-square-warning-solid","chat-bubble-text-square","chat-bubble-text-square-remix","chat-bubble-text-square-solid","chat-two-bubbles-oval","chat-two-bubbles-oval-remix","chat-two-bubbles-oval-solid","email-attachment-document","email-attachment-document-remix","email-attachment-document-solid","inbox-content","inbox-content-remix","inbox-content-solid","inbox-post","inbox-post-remix","inbox-post-solid","lock-comment-security","lock-comment-security-solid","mail-notification","mail-notification-remix","mail-notification-solid","mail-outgoing","mail-outgoing-remix","mail-outgoing-solid","mail-search","mail-search-remix","mail-search-solid","mail-send","mail-send-email-message","mail-send-email-message-remix","mail-send-email-message-solid","mail-send-remix","mail-send-reply-all","mail-send-reply-all-remix","mail-send-reply-all-solid","mail-send-solid","mail-setting","mail-setting-gear-remix","mail-setting-solid","reply-to-message-typing","reply-to-message-typing-remix","reply-to-message-typing-solid","sad-face","sad-face-remix","sad-face-solid","sign-at","sign-at-remix","sign-at-solid","smiley-drool","smiley-drool-remix","smiley-drool-solid","smiley-indiferent","smiley-indiferent-remix","smiley-indiferent-solid","smiley-laughing-1","smiley-laughing-1-remix","smiley-laughing-1-solid","smiley-sparks","smiley-sparks-remix","smiley-sparks-solid"],"MapTravel":["airport-security","airport-security-remix","airport-security-solid","beach","beach-remix","beach-solid","bell","bell-remix","bell-solid","bicycle-bike","bicycle-bike-remix","bicycle-bike-solid","braille-blind","braille-blind-remix","braille-blind-solid","building-office","building-office-remix","building-office-solid","bus","bus-remix","bus-solid","earth-1","earth-1-solid","earth-2-remix","electric-charging-station","electric-charging-station-remix","electric-charging-station-solid","escalator-up","escalator-up-remix","escalator-up-solid","fire-evacuation","fire-evacuation-remix","fire-evacuation-solid","government-building-1","government-building-1-remix","government-building-1-solid","high-speed-train-side","high-speed-train-side-remix","high-speed-train-side-solid","hot-air-balloon","hot-air-balloon-remix","hot-air-balloon-solid","hot-spring","hot-spring-solid","hotel-bed-5","hotel-bed-5-remix","hotel-bed-5-solid","hotel-five-star","hotel-five-star-remix","hotel-five-star-solid","information-desk","information-desk-remix","information-desk-solid","intellectual","intellectual-remix","intellectual-solid","intersex-symbol","intersex-symbol-remix","intersex-symbol-solid","landing","landing-remix","landing-solid","lift","lift-remix","lift-solid","location-heart-pin","location-heart-pin-remix","location-heart-pin-solid","location-pin","location-pin-3","location-pin-3-remix","location-pin-3-solid","location-pin-disabled","location-pin-disabled-remix","location-pin-disabled-solid","location-pin-remix","location-pin-solid","lost-and-found","lost-and-found-remix","lost-and-found-solid","man-arm-raises-2-alternate","man-arm-raises-2-alternate-remix","man-arm-raises-2-alternate-solid","map-fold","map-fold-remix","map-fold-solid","map-location-star-pin","map-location-star-pin-remix","map-location-star-pin-solid","navigation-arrow-off","navigation-arrow-off-remix","navigation-arrow-off-solid","no-smaking-area","no-smaking-area-remix","no-smaking-area-solid","painting-board","painting-board-remix","painting-board-solid","park","park-remix","park-solid","pet-paw","pet-paw-remix","pet-paw-solid","pool-ladder","pool-ladder-remix","pool-ladder-solid","rectangle-flag","rectangle-flag-remix","rectangle-flag-solid","sail-ship","sail-ship-remix","sail-ship-solid","smoking-area","smoking-area-remix","smoking-area-solid","street-sign","street-sign-remix","street-sign-solid","stroller","stroller-remix","stroller-solid","suitcase-rolling","suitcase-rolling-remix","suitcase-rolling-solid","theater-mask","theater-mask-remix","theater-mask-solid","toilet-man","toilet-man-remix","toilet-man-solid","toilet-sign-man","toilet-sign-man-remix","toilet-sign-man-solid","toilet-women","toilet-women-remix","toilet-women-solid","traffic-light","traffic-light-remix","traffic-light-solid","travel-places-hot-spring-remix","user-pin","user-pin-remix","user-pin-solid","visual-blind","visual-blind-remix","visual-blind-solid","wheelchair-2","wheelchair-2-remix","wheelchair-2-solid"],"MoneyShopping":["announcement-megaphone","announcement-megaphone-remix","announcement-megaphone-solid","bag","bag-remix","bag-solid","bag-suitcase-4","bag-suitcase-4-remix","bag-suitcase-4-solid","ball","ball-remix","ball-solid","bill-1-remix","bitcoin-circle-1","bitcoin-circle-1-remix","bitcoin-circle-1-solid","business-progress-bar-2","business-progress-bar-2-remix","business-progress-bar-2-solid","calculator-1","calculator-1-remix","calculator-1-solid","credit-card-5","credit-card-5-remix","credit-card-5-solid","diamond-1","diamond-1-solid","diamond-2-remix","discount-percent-cutout","discount-percent-cutout-remix","discount-percent-cutout-solid","document-certificate","document-certificate-remix","document-certificate-solid","dollar-coin","dollar-coin-remix","dollar-coin-solid","factory-plant","factory-plant-remix","factory-plant-solid","gift","gift-remix","gift-solid","gold","gold-remix","gold-solid","graph-arrow-user-increase","graph-arrow-user-increase-remix","graph-arrow-user-increase-solid","graph-bar-increase","graph-bar-increase-remix","graph-bar-increase-solid","graph-dot","graph-dot-remix","graph-dot-solid","justice-scale-2","justice-scale-2-remix","justice-scale-2-solid","lipstick","lipstick-remix","lipstick-solid","mall","mall-remix","mall-solid","money-cash-bill-1","money-cash-bill-1-solid","moustache","moustache-remix","moustache-solid","payment-recieve-7","payment-recieve-7-remix","payment-recieve-7-solid","piggy-bank","piggy-bank-remix","piggy-bank-solid","pound-circle","pound-circle-remix","pound-circle-solid","production-belt","production-belt-remix","production-belt-solid","receipt-cross","receipt-cross-remix","receipt-cross-solid","safe-vault","safe-vault-remix","safe-vault-solid","shopping-basket-1","shopping-basket-1-remix","shopping-basket-1-solid","shopping-cart-add","shopping-cart-add-remix","shopping-cart-add-solid","sofa","sofa-remix","sofa-solid","stock","stock-remix","stock-solid","stool","stool-remix","stool-solid","store-1-remix","store-2","store-2-solid","tag-alt","tag-alt-remix","tag-alt-solid","target-3","target-3-remix","target-3-solid","treasure-chest","treasure-chest-remix","treasure-chest-solid","wallet","wallet-remix","wallet-solid"],"NatureEcology":["alien","alien-remix","alien-solid","atom","atom-remix","atom-solid","dna","dna-remix","dna-solid","dog-1","dog-1-remix","dog-1-solid","erlenmeyer-flask","erlenmeyer-flask-remix","erlenmeyer-flask-solid","galaxy-2","galaxy-2-remix","galaxy-2-solid","global-warming-2","global-warming-2-remix","global-warming-2-solid","industry-innovation-and-infrastructure","industry-innovation-and-infrastructure-remix","industry-innovation-and-infrastructure-solid","leaf-protect","leaf-protect-remix","leaf-protect-solid","log","log-remix","log-solid","no-poverty","no-poverty-remix","no-poverty-solid","potted-flower","potted-flower-remix","potted-flower-solid","recycle-1","recycle-1-remix","recycle-1-solid","recycle-bin","recycle-bin-remix","recycle-bin-solid","reduced-inequalities","reduced-inequalities-remix","reduced-inequalities-solid","sunset","sunset-remix","sunset-solid","telescope","telescope-remix","telescope-solid","test-tube","test-tube-remix","test-tube-solid","tree-1","tree-1-remix","tree-1-solid","world","world-remix","world-solid"],"Phone":["airplane-disabled","airplane-disabled-remix","airplane-disabled-solid","airplane-enabled","airplane-enabled-remix","airplane-enabled-solid","call-hang-up","call-hang-up-remix","call-hang-up-solid","contact-phonebook","contact-phonebook-remix","contact-phonebook-solid","notification-alarm-snooze","notification-alarm-snooze-remix","notification-alarm-snooze-solid","notification-alert","notification-alert-remix","notification-alert-solid","phone","phone-remix","phone-solid","phone-vibrate","phone-vibrate-remix","phone-vibrate-solid","signal-full","signal-full-remix","signal-full-solid"],"Programming":["application-add","application-add-remix","application-add-solid","browser-code-1","browser-code-1-remix","browser-code-1-solid","browser-website-1","browser-website-1-remix","browser-website-1-solid","bug","bug-remix","bug-solid","bug-virus-browser","bug-virus-browser-remix","bug-virus-browser-solid","cloud-data-transfer","cloud-data-transfer-remix","cloud-data-transfer-solid","cloud-off","cloud-off-remix","cloud-off-solid","code-monitor-2","code-monitor-2-remix","code-monitor-2-solid","drop-down-menu","drop-down-menu-remix","drop-down-menu-solid","html-five","html-five-remix","html-five-solid","incognito-mode","incognito-mode-remix","incognito-mode-solid","module","module-remix","module-solid","rss-square","rss-square-remix","rss-square-solid","script-2","script-2-remix","script-2-solid","steps-1","steps-1-remix","steps-1-solid","threat-phone","threat-phone-remix","threat-phone-solid","web","web-remix","web-solid","widget","widget-remix","widget-solid"],"Shipping":["box-waterproof","box-waterproof-remix","box-waterproof-solid","fragile","fragile-remix","fragile-solid","parachute-drop","parachute-drop-remix","parachute-drop-solid","shipment-upload","shipment-upload-solid","shipping-box-1","shipping-box-1-remix","shipping-box-1-solid","warehouse-1","warehouse-1-remix","warehouse-1-solid"],"WorkEducation":["class-lesson","class-lesson-remix","class-lesson-solid","global-learning","global-learning-remix","global-learning-solid","graduation-cap","graduation-cap-remix","graduation-cap-solid","office-worker","office-worker-remix","office-worker-solid","task-list-edit","task-list-edit-remix","task-list-edit-solid","workspace-desk","workspace-desk-remix","workspace-desk-solid"]}}
